setup.py
VirtualEnvManager.egg-info/PKG-INFO
VirtualEnvManager.egg-info/SOURCES.txt
VirtualEnvManager.egg-info/dependency_links.txt
VirtualEnvManager.egg-info/entry_points.txt
VirtualEnvManager.egg-info/requires.txt
VirtualEnvManager.egg-info/top_level.txt
vem/__init__.py
vem/manager.py