Metadata-Version: 1.0
Name: VirtualEnvManager
Version: 0.3
Summary: A package to manage various virtual environments.
Home-page: UNKNOWN
Author: Diez B. Roggisch
Author-email: deets@web.de
License: PSF
Keywords: python virtualenv
Platform: UNKNOWN
